CONTRIBUTING.md
LICENSE
MANIFEST.in
Makefile
README.md
pyproject.toml
requirements.txt
setup.py
web_scraper/main.py
web_scraper/tests.py
web_scraper_python_library.egg-info/PKG-INFO
web_scraper_python_library.egg-info/SOURCES.txt
web_scraper_python_library.egg-info/dependency_links.txt
web_scraper_python_library.egg-info/requires.txt
web_scraper_python_library.egg-info/top_level.txt